stormy/__init__.py
stormy/datamodule.py
stormy/module.py
stormy/trainer.py
stormy/utils.py
stormy_ai-1.0.1a9.dist-info/METADATA
stormy_ai-1.0.1a9.dist-info/WHEEL
stormy_ai-1.0.1a9.dist-info/entry_points.txt
stormy_ai-1.0.1a9.dist-info/RECORD
