Metadata-Version: 2.4
Name: stormy-ai
Version: 1.0.1a9
Summary: Add your description here
Author-email: Cozmo <107803920+Cozmo18@users.noreply.github.com>
Requires-Python: >=3.10
Requires-Dist: datasets>=4.0.0
Requires-Dist: jsonargparse[signatures]>=4.40.0
Requires-Dist: lightning==2.4
Requires-Dist: mlflow>=3.1.1
Requires-Dist: numpy<2
Requires-Dist: torch==2.2.2
Requires-Dist: transformers==4.49
